[{"url":"https://api.github.com/repos/stefansundin/altdrag/releases/1700287","assets_url":"https://api.github.com/repos/stefansundin/altdrag/releases/1700287/assets","upload_url":"https://uploads.github.com/repos/stefansundin/altdrag/releases/1700287/assets{?name}","html_url":"https://github.com/stefansundin/altdrag/releases/tag/v1.1b1","id":1700287,"tag_name":"v1.1b1","target_commitish":"master","name":"AltDrag v1.1 beta","draft":false,"author":{"login":"stefansundin","id":1991151,"avatar_url":"https://avatars.githubusercontent.com/u/1991151?v=3","gravatar_id":"","url":"https://api.github.com/users/stefansundin","html_url":"https://github.com/stefansundin","followers_url":"https://api.github.com/users/stefansundin/followers","following_url":"https://api.github.com/users/stefansundin/following{/other_user}","gists_url":"https://api.github.com/users/stefansundin/gists{/gist_id}","starred_url":"https://api.github.com/users/stefansundin/starred{/owner}{/repo}","subscriptions_url":"https://api.github.com/users/stefansundin/subscriptions","organizations_url":"https://api.github.com/users/stefansundin/orgs","repos_url":"https://api.github.com/users/stefansundin/repos","events_url":"https://api.github.com/users/stefansundin/events{/privacy}","received_events_url":"https://api.github.com/users/stefansundin/received_events","type":"User","site_admin":false},"prerelease":true,"created_at":"2015-08-20T16:21:32Z","published_at":"2015-08-20T16:37:20Z","assets":[{"url":"https://api.github.com/repos/stefansundin/altdrag/releases/assets/803876","id":803876,"name":"AltDrag-1.1b1.exe","label":null,"uploader":{"login":"stefansundin","id":1991151,"avatar_url":"https://avatars.githubusercontent.com/u/1991151?v=3","gravatar_id":"","url":"https://api.github.com/users/stefansundin","html_url":"https://github.com/stefansundin","followers_url":"https://api.github.com/users/stefansundin/followers","following_url":"https://api.github.com/users/stefansundin/following{/other_user}","gists_url":"https://api.github.com/users/stefansundin/gists{/gist_id}","starred_url":"https://api.github.com/users/stefansundin/starred{/owner}{/repo}","subscriptions_url":"https://api.github.com/users/stefansundin/subscriptions","organizations_url":"https://api.github.com/users/stefansundin/orgs","repos_url":"https://api.github.com/users/stefansundin/repos","events_url":"https://api.github.com/users/stefansundin/events{/privacy}","received_events_url":"https://api.github.com/users/stefansundin/received_events","type":"User","site_admin":false},"content_type":"application/x-msdownload","state":"uploaded","size":194957,"download_count":26,"created_at":"2015-08-20T16:35:05Z","updated_at":"2015-08-20T16:35:07Z","browser_download_url":"https://github.com/stefansundin/altdrag/releases/download/v1.1b1/AltDrag-1.1b1.exe"},{"url":"https://api.github.com/repos/stefansundin/altdrag/releases/assets/803878","id":803878,"name":"AltDrag-1.1b1.zip","label":null,"uploader":{"login":"stefansundin","id":1991151,"avatar_url":"https://avatars.githubusercontent.com/u/1991151?v=3","gravatar_id":"","url":"https://api.github.com/users/stefansundin","html_url":"https://github.com/stefansundin","followers_url":"https://api.github.com/users/stefansundin/followers","following_url":"https://api.github.com/users/stefansundin/following{/other_user}","gists_url":"https://api.github.com/users/stefansundin/gists{/gist_id}","starred_url":"https://api.github.com/users/stefansundin/starred{/owner}{/repo}","subscriptions_url":"https://api.github.com/users/stefansundin/subscriptions","organizations_url":"https://api.github.com/users/stefansundin/orgs","repos_url":"https://api.github.com/users/stefansundin/repos","events_url":"https://api.github.com/users/stefansundin/events{/privacy}","received_events_url":"https://api.github.com/users/stefansundin/received_events","type":"User","site_admin":false},"content_type":"application/x-zip-compressed","state":"uploaded","size":88936,"download_count":5,"created_at":"2015-08-20T16:35:11Z","updated_at":"2015-08-20T16:35:12Z","browser_download_url":"https://github.com/stefansundin/altdrag/releases/download/v1.1b1/AltDrag-1.1b1.zip"}],"tarball_url":"https://api.github.com/repos/stefansundin/altdrag/tarball/v1.1b1","zipball_url":"https://api.github.com/repos/stefansundin/altdrag/zipball/v1.1b1","body":"[Get RSS updates by subscribing to the release feed.](https://github.com/stefansundin/altdrag/releases.atom)\r\n\r\n2015-08-20:\r\n- AltDrag has moved to GitHub.\r\n- The installer now defaults to installing to your `%APPDATA%` directory.\r\n  - This means it no longer asks for administrator privileges.\r\n  - **I recommend everyone to uninstall and then install from scratch.**\r\n  - You can still install to `C:\\Program Files\\` if you right-click the installer and use `Run as administrator`.\r\n- Fixed the shift key not being usable after dragging started (Windows 10).\r\n"},{"url":"https://api.github.com/repos/stefansundin/altdrag/releases/816276","assets_url":"https://api.github.com/repos/stefansundin/altdrag/releases/816276/assets","upload_url":"https://uploads.github.com/repos/stefansundin/altdrag/releases/816276/assets{?name}","html_url":"https://github.com/stefansundin/altdrag/releases/tag/windowfinder-v0.2","id":816276,"tag_name":"windowfinder-v0.2","target_commitish":"master","name":"WindowFinder v0.2","draft":false,"author":{"login":"stefansundin","id":1991151,"avatar_url":"https://avatars.githubusercontent.com/u/1991151?v=3","gravatar_id":"","url":"https://api.github.com/users/stefansundin","html_url":"https://github.com/stefansundin","followers_url":"https://api.github.com/users/stefansundin/followers","following_url":"https://api.github.com/users/stefansundin/following{/other_user}","gists_url":"https://api.github.com/users/stefansundin/gists{/gist_id}","starred_url":"https://api.github.com/users/stefansundin/starred{/owner}{/repo}","subscriptions_url":"https://api.github.com/users/stefansundin/subscriptions","organizations_url":"https://api.github.com/users/stefansundin/orgs","repos_url":"https://api.github.com/users/stefansundin/repos","events_url":"https://api.github.com/users/stefansundin/events{/privacy}","received_events_url":"https://api.github.com/users/stefansundin/received_events","type":"User","site_admin":false},"prerelease":false,"created_at":"2009-09-07T17:10:10Z","published_at":"2014-12-30T20:44:20Z","assets":[{"url":"https://api.github.com/repos/stefansundin/altdrag/releases/assets/360898","id":360898,"name":"WindowFinder-0.2.exe","label":null,"uploader":{"login":"stefansundin","id":1991151,"avatar_url":"https://avatars.githubusercontent.com/u/1991151?v=3","gravatar_id":"","url":"https://api.github.com/users/stefansundin","html_url":"https://github.com/stefansundin","followers_url":"https://api.github.com/users/stefansundin/followers","following_url":"https://api.github.com/users/stefansundin/following{/other_user}","gists_url":"https://api.github.com/users/stefansundin/gists{/gist_id}","starred_url":"https://api.github.com/users/stefansundin/starred{/owner}{/repo}","subscriptions_url":"https://api.github.com/users/stefansundin/subscriptions","organizations_url":"https://api.github.com/users/stefansundin/orgs","repos_url":"https://api.github.com/users/stefansundin/repos","events_url":"https://api.github.com/users/stefansundin/events{/privacy}","received_events_url":"https://api.github.com/users/stefansundin/received_events","type":"User","site_admin":false},"content_type":"application/x-msdownload","state":"uploaded","size":54628,"download_count":1,"created_at":"2014-12-30T20:47:10Z","updated_at":"2014-12-30T20:47:13Z","browser_download_url":"https://github.com/stefansundin/altdrag/releases/download/windowfinder-v0.2/WindowFinder-0.2.exe"}],"tarball_url":"https://api.github.com/repos/stefansundin/altdrag/tarball/windowfinder-v0.2","zipball_url":"https://api.github.com/repos/stefansundin/altdrag/zipball/windowfinder-v0.2","body":"2009-09-07"},{"url":"https://api.github.com/repos/stefansundin/altdrag/releases/816265","assets_url":"https://api.github.com/repos/stefansundin/altdrag/releases/816265/assets","upload_url":"https://uploads.github.com/repos/stefansundin/altdrag/releases/816265/assets{?name}","html_url":"https://github.com/stefansundin/altdrag/releases/tag/windowfinder-v0.1","id":816265,"tag_name":"windowfinder-v0.1","target_commitish":"master","name":"WindowFinder v0.1","draft":false,"author":{"login":"stefansundin","id":1991151,"avatar_url":"https://avatars.githubusercontent.com/u/1991151?v=3","gravatar_id":"","url":"https://api.github.com/users/stefansundin","html_url":"https://github.com/stefansundin","followers_url":"https://api.github.com/users/stefansundin/followers","following_url":"https://api.github.com/users/stefansundin/following{/other_user}","gists_url":"https://api.github.com/users/stefansundin/gists{/gist_id}","starred_url":"https://api.github.com/users/stefansundin/starred{/owner}{/repo}","subscriptions_url":"https://api.github.com/users/stefansundin/subscriptions","organizations_url":"https://api.github.com/users/stefansundin/orgs","repos_url":"https://api.github.com/users/stefansundin/repos","events_url":"https://api.github.com/users/stefansundin/events{/privacy}","received_events_url":"https://api.github.com/users/stefansundin/received_events","type":"User","site_admin":false},"prerelease":false,"created_at":"2009-01-12T18:10:10Z","published_at":"2014-12-30T20:41:08Z","assets":[{"url":"https://api.github.com/repos/stefansundin/altdrag/releases/assets/360885","id":360885,"name":"WindowFinder-0.1.7z","label":null,"uploader":{"login":"stefansundin","id":1991151,"avatar_url":"https://avatars.githubusercontent.com/u/1991151?v=3","gravatar_id":"","url":"https://api.github.com/users/stefansundin","html_url":"https://github.com/stefansundin","followers_url":"https://api.github.com/users/stefansundin/followers","following_url":"https://api.github.com/users/stefansundin/following{/other_user}","gists_url":"https://api.github.com/users/stefansundin/gists{/gist_id}","starred_url":"https://api.github.com/users/stefansundin/starred{/owner}{/repo}","subscriptions_url":"https://api.github.com/users/stefansundin/subscriptions","organizations_url":"https://api.github.com/users/stefansundin/orgs","repos_url":"https://api.github.com/users/stefansundin/repos","events_url":"https://api.github.com/users/stefansundin/events{/privacy}","received_events_url":"https://api.github.com/users/stefansundin/received_events","type":"User","site_admin":false},"content_type":"application/octet-stream","state":"uploaded","size":11915,"download_count":1,"created_at":"2014-12-30T20:40:53Z","updated_at":"2014-12-30T20:40:54Z","browser_download_url":"https://github.com/stefansundin/altdrag/releases/download/windowfinder-v0.1/WindowFinder-0.1.7z"}],"tarball_url":"https://api.github.com/repos/stefansundin/altdrag/tarball/windowfinder-v0.1","zipball_url":"https://api.github.com/repos/stefansundin/altdrag/zipball/windowfinder-v0.1","body":"2009-01-12"},{"url":"https://api.github.com/repos/stefansundin/altdrag/releases/814293","assets_url":"https://api.github.com/repos/stefansundin/altdrag/releases/814293/assets","upload_url":"https://uploads.github.com/repos/stefansundin/altdrag/releases/814293/assets{?name}","html_url":"https://github.com/stefansundin/altdrag/releases/tag/v1.0rc","id":814293,"tag_name":"v1.0rc","target_commitish":"master","name":"AltDrag v1.0rc","draft":false,"author":{"login":"stefansundin","id":1991151,"avatar_url":"https://avatars.githubusercontent.com/u/1991151?v=3","gravatar_id":"","url":"https://api.github.com/users/stefansundin","html_url":"https://github.com/stefansundin","followers_url":"https://api.github.com/users/stefansundin/followers","following_url":"https://api.github.com/users/stefansundin/following{/other_user}","gists_url":"https://api.github.com/users/stefansundin/gists{/gist_id}","starred_url":"https://api.github.com/users/stefansundin/starred{/owner}{/repo}","subscriptions_url":"https://api.github.com/users/stefansundin/subscriptions","organizations_url":"https://api.github.com/users/stefansundin/orgs","repos_url":"https://api.github.com/users/stefansundin/repos","events_url":"https://api.github.com/users/stefansundin/events{/privacy}","received_events_url":"https://api.github.com/users/stefansundin/received_events","type":"User","site_admin":false},"prerelease":true,"created_at":"2013-09-06T19:03:47Z","published_at":"2014-12-29T22:49:39Z","assets":[{"url":"https://api.github.com/repos/stefansundin/altdrag/releases/assets/359885","id":359885,"name":"AltDrag-1.0rc.7z","label":null,"uploader":{"login":"stefansundin","id":1991151,"avatar_url":"https://avatars.githubusercontent.com/u/1991151?v=3","gravatar_id":"","url":"https://api.github.com/users/stefansundin","html_url":"https://github.com/stefansundin","followers_url":"https://api.github.com/users/stefansundin/followers","following_url":"https://api.github.com/users/stefansundin/following{/other_user}","gists_url":"https://api.github.com/users/stefansundin/gists{/gist_id}","starred_url":"https://api.github.com/users/stefansundin/starred{/owner}{/repo}","subscriptions_url":"https://api.github.com/users/stefansundin/subscriptions","organizations_url":"https://api.github.com/users/stefansundin/orgs","repos_url":"https://api.github.com/users/stefansundin/repos","events_url":"https://api.github.com/users/stefansundin/events{/privacy}","received_events_url":"https://api.github.com/users/stefansundin/received_events","type":"User","site_admin":false},"content_type":"application/octet-stream","state":"uploaded","size":60972,"download_count":5,"created_at":"2014-12-29T22:49:11Z","updated_at":"2014-12-29T22:49:26Z","browser_download_url":"https://github.com/stefansundin/altdrag/releases/download/v1.0rc/AltDrag-1.0rc.7z"},{"url":"https://api.github.com/repos/stefansundin/altdrag/releases/assets/359886","id":359886,"name":"AltDrag-1.0rc.exe","label":null,"uploader":{"login":"stefansundin","id":1991151,"avatar_url":"https://avatars.githubusercontent.com/u/1991151?v=3","gravatar_id":"","url":"https://api.github.com/users/stefansundin","html_url":"https://github.com/stefansundin","followers_url":"https://api.github.com/users/stefansundin/followers","following_url":"https://api.github.com/users/stefansundin/following{/other_user}","gists_url":"https://api.github.com/users/stefansundin/gists{/gist_id}","starred_url":"https://api.github.com/users/stefansundin/starred{/owner}{/repo}","subscriptions_url":"https://api.github.com/users/stefansundin/subscriptions","organizations_url":"https://api.github.com/users/stefansundin/orgs","repos_url":"https://api.github.com/users/stefansundin/repos","events_url":"https://api.github.com/users/stefansundin/events{/privacy}","received_events_url":"https://api.github.com/users/stefansundin/received_events","type":"User","site_admin":false},"content_type":"application/x-msdownload","state":"uploaded","size":190724,"download_count":3,"created_at":"2014-12-29T22:49:12Z","updated_at":"2014-12-29T22:49:38Z","browser_download_url":"https://github.com/stefansundin/altdrag/releases/download/v1.0rc/AltDrag-1.0rc.exe"}],"tarball_url":"https://api.github.com/repos/stefansundin/altdrag/tarball/v1.0rc","zipball_url":"https://api.github.com/repos/stefansundin/altdrag/zipball/v1.0rc","body":"2013-09-06:\r\n- Add support for MDI windows. Works with many features (e.g. `HookWindows`, `AltTab` scrolling, snapping).\r\n- Add ability to lower windows by middle clicking title bars.\r\n- Add ability to translate AltDrag with an ini file.\r\n- Many small fixes for multiple monitors.\r\n- Made the corner regions for resizing bigger, now corners are 38% and middle regions 24%. Before all regions were 33%.\r\n- Fixed `HookWindows` sometimes blocking the space key.\r\n- Fixed a few issues with `InactiveScroll`."},{"url":"https://api.github.com/repos/stefansundin/altdrag/releases/814292","assets_url":"https://api.github.com/repos/stefansundin/altdrag/releases/814292/assets","upload_url":"https://uploads.github.com/repos/stefansundin/altdrag/releases/814292/assets{?name}","html_url":"https://github.com/stefansundin/altdrag/releases/tag/v1.0b3","id":814292,"tag_name":"v1.0b3","target_commitish":"master","name":"AltDrag v1.0b3","draft":false,"author":{"login":"stefansundin","id":1991151,"avatar_url":"https://avatars.githubusercontent.com/u/1991151?v=3","gravatar_id":"","url":"https://api.github.com/users/stefansundin","html_url":"https://github.com/stefansundin","followers_url":"https://api.github.com/users/stefansundin/followers","following_url":"https://api.github.com/users/stefansundin/following{/other_user}","gists_url":"https://api.github.com/users/stefansundin/gists{/gist_id}","starred_url":"https://api.github.com/users/stefansundin/starred{/owner}{/repo}","subscriptions_url":"https://api.github.com/users/stefansundin/subscriptions","organizations_url":"https://api.github.com/users/stefansundin/orgs","repos_url":"https://api.github.com/users/stefansundin/repos","events_url":"https://api.github.com/users/stefansundin/events{/privacy}","received_events_url":"https://api.github.com/users/stefansundin/received_events","type":"User","site_admin":false},"prerelease":true,"created_at":"2013-06-20T17:10:10Z","published_at":"2014-12-30T20:16:47Z","assets":[{"url":"https://api.github.com/repos/stefansundin/altdrag/releases/assets/359884","id":359884,"name":"AltDrag-1.0b3-2.exe","label":null,"uploader":{"login":"stefansundin","id":1991151,"avatar_url":"https://avatars.githubusercontent.com/u/1991151?v=3","gravatar_id":"","url":"https://api.github.com/users/stefansundin","html_url":"https://github.com/stefansundin","followers_url":"https://api.github.com/users/stefansundin/followers","following_url":"https://api.github.com/users/stefansundin/following{/other_user}","gists_url":"https://api.github.com/users/stefansundin/gists{/gist_id}","starred_url":"https://api.github.com/users/stefansundin/starred{/owner}{/repo}","subscriptions_url":"https://api.github.com/users/stefansundin/subscriptions","organizations_url":"https://api.github.com/users/stefansundin/orgs","repos_url":"https://api.github.com/users/stefansundin/repos","events_url":"https://api.github.com/users/stefansundin/events{/privacy}","received_events_url":"https://api.github.com/users/stefansundin/received_events","type":"User","site_admin":false},"content_type":"application/x-msdownload","state":"uploaded","size":181376,"download_count":2,"created_at":"2014-12-29T22:48:09Z","updated_at":"2014-12-29T22:48:19Z","browser_download_url":"https://github.com/stefansundin/altdrag/releases/download/v1.0b3/AltDrag-1.0b3-2.exe"},{"url":"https://api.github.com/repos/stefansundin/altdrag/releases/assets/359883","id":359883,"name":"AltDrag-1.0b3.7z","label":null,"uploader":{"login":"stefansundin","id":1991151,"avatar_url":"https://avatars.githubusercontent.com/u/1991151?v=3","gravatar_id":"","url":"https://api.github.com/users/stefansundin","html_url":"https://github.com/stefansundin","followers_url":"https://api.github.com/users/stefansundin/followers","following_url":"https://api.github.com/users/stefansundin/following{/other_user}","gists_url":"https://api.github.com/users/stefansundin/gists{/gist_id}","starred_url":"https://api.github.com/users/stefansundin/starred{/owner}{/repo}","subscriptions_url":"https://api.github.com/users/stefansundin/subscriptions","organizations_url":"https://api.github.com/users/stefansundin/orgs","repos_url":"https://api.github.com/users/stefansundin/repos","events_url":"https://api.github.com/users/stefansundin/events{/privacy}","received_events_url":"https://api.github.com/users/stefansundin/received_events","type":"User","site_admin":false},"content_type":"application/octet-stream","state":"uploaded","size":56210,"download_count":2,"created_at":"2014-12-29T22:48:09Z","updated_at":"2014-12-29T22:48:16Z","browser_download_url":"https://github.com/stefansundin/altdrag/releases/download/v1.0b3/AltDrag-1.0b3.7z"},{"url":"https://api.github.com/repos/stefansundin/altdrag/releases/assets/359882","id":359882,"name":"AltDrag-1.0b3.exe","label":null,"uploader":{"login":"stefansundin","id":1991151,"avatar_url":"https://avatars.githubusercontent.com/u/1991151?v=3","gravatar_id":"","url":"https://api.github.com/users/stefansundin","html_url":"https://github.com/stefansundin","followers_url":"https://api.github.com/users/stefansundin/followers","following_url":"https://api.github.com/users/stefansundin/following{/other_user}","gists_url":"https://api.github.com/users/stefansundin/gists{/gist_id}","starred_url":"https://api.github.com/users/stefansundin/starred{/owner}{/repo}","subscriptions_url":"https://api.github.com/users/stefansundin/subscriptions","organizations_url":"https://api.github.com/users/stefansundin/orgs","repos_url":"https://api.github.com/users/stefansundin/repos","events_url":"https://api.github.com/users/stefansundin/events{/privacy}","received_events_url":"https://api.github.com/users/stefansundin/received_events","type":"User","site_admin":false},"content_type":"application/x-msdownload","state":"uploaded","size":195366,"download_count":2,"created_at":"2014-12-29T22:48:08Z","updated_at":"2014-12-29T22:48:15Z","browser_download_url":"https://github.com/stefansundin/altdrag/releases/download/v1.0b3/AltDrag-1.0b3.exe"}],"tarball_url":"https://api.github.com/repos/stefansundin/altdrag/tarball/v1.0b3","zipball_url":"https://api.github.com/repos/stefansundin/altdrag/zipball/v1.0b3","body":"2013-06-20:\r\n- If you enable `InactiveScroll`, you can now hold the shift key to scroll horizontally. Note that this only works in programs that have implemented horizontal scrolling.\r\n- New scroll action: `Transparency`. It allows you to set the transparency of arbitrary windows.\r\n- The code that prevents the window menu from triggering has been reworked to work with Internet Explorer."},{"url":"https://api.github.com/repos/stefansundin/altdrag/releases/814291","assets_url":"https://api.github.com/repos/stefansundin/altdrag/releases/814291/assets","upload_url":"https://uploads.github.com/repos/stefansundin/altdrag/releases/814291/assets{?name}","html_url":"https://github.com/stefansundin/altdrag/releases/tag/v1.0b2","id":814291,"tag_name":"v1.0b2","target_commitish":"master","name":"AltDrag v1.0b2","draft":false,"author":{"login":"stefansundin","id":1991151,"avatar_url":"https://avatars.githubusercontent.com/u/1991151?v=3","gravatar_id":"","url":"https://api.github.com/users/stefansundin","html_url":"https://github.com/stefansundin","followers_url":"https://api.github.com/users/stefansundin/followers","following_url":"https://api.github.com/users/stefansundin/following{/other_user}","gists_url":"https://api.github.com/users/stefansundin/gists{/gist_id}","starred_url":"https://api.github.com/users/stefansundin/starred{/owner}{/repo}","subscriptions_url":"https://api.github.com/users/stefansundin/subscriptions","organizations_url":"https://api.github.com/users/stefansundin/orgs","repos_url":"https://api.github.com/users/stefansundin/repos","events_url":"https://api.github.com/users/stefansundin/events{/privacy}","received_events_url":"https://api.github.com/users/stefansundin/received_events","type":"User","site_admin":false},"prerelease":true,"created_at":"2013-04-20T17:10:10Z","published_at":"2014-12-29T22:46:59Z","assets":[{"url":"https://api.github.com/repos/stefansundin/altdrag/releases/assets/359880","id":359880,"name":"AltDrag-1.0b2.7z","label":null,"uploader":{"login":"stefansundin","id":1991151,"avatar_url":"https://avatars.githubusercontent.com/u/1991151?v=3","gravatar_id":"","url":"https://api.github.com/users/stefansundin","html_url":"https://github.com/stefansundin","followers_url":"https://api.github.com/users/stefansundin/followers","following_url":"https://api.github.com/users/stefansundin/following{/other_user}","gists_url":"https://api.github.com/users/stefansundin/gists{/gist_id}","starred_url":"https://api.github.com/users/stefansundin/starred{/owner}{/repo}","subscriptions_url":"https://api.github.com/users/stefansundin/subscriptions","organizations_url":"https://api.github.com/users/stefansundin/orgs","repos_url":"https://api.github.com/users/stefansundin/repos","events_url":"https://api.github.com/users/stefansundin/events{/privacy}","received_events_url":"https://api.github.com/users/stefansundin/received_events","type":"User","site_admin":false},"content_type":"application/octet-stream","state":"uploaded","size":55933,"download_count":2,"created_at":"2014-12-29T22:46:25Z","updated_at":"2014-12-29T22:46:32Z","browser_download_url":"https://github.com/stefansundin/altdrag/releases/download/v1.0b2/AltDrag-1.0b2.7z"},{"url":"https://api.github.com/repos/stefansundin/altdrag/releases/assets/359881","id":359881,"name":"AltDrag-1.0b2.exe","label":null,"uploader":{"login":"stefansundin","id":1991151,"avatar_url":"https://avatars.githubusercontent.com/u/1991151?v=3","gravatar_id":"","url":"https://api.github.com/users/stefansundin","html_url":"https://github.com/stefansundin","followers_url":"https://api.github.com/users/stefansundin/followers","following_url":"https://api.github.com/users/stefansundin/following{/other_user}","gists_url":"https://api.github.com/users/stefansundin/gists{/gist_id}","starred_url":"https://api.github.com/users/stefansundin/starred{/owner}{/repo}","subscriptions_url":"https://api.github.com/users/stefansundin/subscriptions","organizations_url":"https://api.github.com/users/stefansundin/orgs","repos_url":"https://api.github.com/users/stefansundin/repos","events_url":"https://api.github.com/users/stefansundin/events{/privacy}","received_events_url":"https://api.github.com/users/stefansundin/received_events","type":"User","site_admin":false},"content_type":"application/x-msdownload","state":"uploaded","size":181042,"download_count":2,"created_at":"2014-12-29T22:46:26Z","updated_at":"2014-12-29T22:46:37Z","browser_download_url":"https://github.com/stefansundin/altdrag/releases/download/v1.0b2/AltDrag-1.0b2.exe"}],"tarball_url":"https://api.github.com/repos/stefansundin/altdrag/tarball/v1.0b2","zipball_url":"https://api.github.com/repos/stefansundin/altdrag/zipball/v1.0b2","body":"2013-04-20:\r\n- Merged `Config.exe` with `AltDrag.exe`.\r\n- Made it possible to disable the Alt+Scroll action. It was silly of me to not let you do this in beta 1, sorry!\r\n- Added new Alt+Scroll action that changes the volume.\r\n- You can now press the Space key during a drag to reset any custom `AutoSnap` setting for the duration of the drag.\r\n- AltDrag can now request elevation to administrator privileges on demand, allowing for much easier elevation on autostart.\r\n- AltDrag can now be run in multiple instances, useful if you e.g. want to use Alt+LMB to move and Ctrl+LMB to resize. See `MultipleInstances` in the ini file.\r\n- Added experimental feature `FocusOnTyping` that moves focus to the window the mouse is hovering when you start typing. This is a new approach to the hidden X-Mouse feature in Windows. See the ini file for more details.\r\n- Fixed issue with iTunes."},{"url":"https://api.github.com/repos/stefansundin/altdrag/releases/814270","assets_url":"https://api.github.com/repos/stefansundin/altdrag/releases/814270/assets","upload_url":"https://uploads.github.com/repos/stefansundin/altdrag/releases/814270/assets{?name}","html_url":"https://github.com/stefansundin/altdrag/releases/tag/v1.0b1","id":814270,"tag_name":"v1.0b1","target_commitish":"master","name":"AltDrag v1.0b1","draft":false,"author":{"login":"stefansundin","id":1991151,"avatar_url":"https://avatars.githubusercontent.com/u/1991151?v=3","gravatar_id":"","url":"https://api.github.com/users/stefansundin","html_url":"https://github.com/stefansundin","followers_url":"https://api.github.com/users/stefansundin/followers","following_url":"https://api.github.com/users/stefansundin/following{/other_user}","gists_url":"https://api.github.com/users/stefansundin/gists{/gist_id}","starred_url":"https://api.github.com/users/stefansundin/starred{/owner}{/repo}","subscriptions_url":"https://api.github.com/users/stefansundin/subscriptions","organizations_url":"https://api.github.com/users/stefansundin/orgs","repos_url":"https://api.github.com/users/stefansundin/repos","events_url":"https://api.github.com/users/stefansundin/events{/privacy}","received_events_url":"https://api.github.com/users/stefansundin/received_events","type":"User","site_admin":false},"prerelease":true,"created_at":"2011-07-30T22:15:52Z","published_at":"2014-12-29T22:31:43Z","assets":[{"url":"https://api.github.com/repos/stefansundin/altdrag/releases/assets/359870","id":359870,"name":"AltDrag-1.0b1.7z","label":null,"uploader":{"login":"stefansundin","id":1991151,"avatar_url":"https://avatars.githubusercontent.com/u/1991151?v=3","gravatar_id":"","url":"https://api.github.com/users/stefansundin","html_url":"https://github.com/stefansundin","followers_url":"https://api.github.com/users/stefansundin/followers","following_url":"https://api.github.com/users/stefansundin/following{/other_user}","gists_url":"https://api.github.com/users/stefansundin/gists{/gist_id}","starred_url":"https://api.github.com/users/stefansundin/starred{/owner}{/repo}","subscriptions_url":"https://api.github.com/users/stefansundin/subscriptions","organizations_url":"https://api.github.com/users/stefansundin/orgs","repos_url":"https://api.github.com/users/stefansundin/repos","events_url":"https://api.github.com/users/stefansundin/events{/privacy}","received_events_url":"https://api.github.com/users/stefansundin/received_events","type":"User","site_admin":false},"content_type":"application/octet-stream","state":"uploaded","size":67574,"download_count":2,"created_at":"2014-12-29T22:31:32Z","updated_at":"2014-12-29T22:31:41Z","browser_download_url":"https://github.com/stefansundin/altdrag/releases/download/v1.0b1/AltDrag-1.0b1.7z"}],"tarball_url":"https://api.github.com/repos/stefansundin/altdrag/tarball/v1.0b1","zipball_url":"https://api.github.com/repos/stefansundin/altdrag/zipball/v1.0b1","body":"2011-07-31:\r\n- Added configuration GUI.\r\n- Added ability to scroll through windows with the scrollwheel (like Alt+Tab!).\r\n- Added ability to blacklist by process name.\r\n- Added new mouse action: `Lower`.\r\n- Added performance options `MoveRate` and `ResizeRate`. Increase if dragging or resizing is slow.\r\n- The scroll hook should no longer stop working when locking the screen or resuming the computer from sleep. A timer checks every 5 seconds if the scroll hook is still working, and re-enables it if it is not.\r\n- You can now press Escape to stop AltDrag. Useful if AltDrag gets in a weird state.\r\n- You can now press Ctrl to make AltDrag think the mouse cursor is still inside the current monitor. Should help people who have multiple monitors and want to snap at borders between monitors.\r\n- Installer now grants access to `AltDrag.ini` to all users. Should help people who use UAC.\r\n- Removed `info.txt`. Use the website for help."},{"url":"https://api.github.com/repos/stefansundin/altdrag/releases/814265","assets_url":"https://api.github.com/repos/stefansundin/altdrag/releases/814265/assets","upload_url":"https://uploads.github.com/repos/stefansundin/altdrag/releases/814265/assets{?name}","html_url":"https://github.com/stefansundin/altdrag/releases/tag/v0.9rc1","id":814265,"tag_name":"v0.9rc1","target_commitish":"master","name":"AltDrag v0.9rc1","draft":false,"author":{"login":"stefansundin","id":1991151,"avatar_url":"https://avatars.githubusercontent.com/u/1991151?v=3","gravatar_id":"","url":"https://api.github.com/users/stefansundin","html_url":"https://github.com/stefansundin","followers_url":"https://api.github.com/users/stefansundin/followers","following_url":"https://api.github.com/users/stefansundin/following{/other_user}","gists_url":"https://api.github.com/users/stefansundin/gists{/gist_id}","starred_url":"https://api.github.com/users/stefansundin/starred{/owner}{/repo}","subscriptions_url":"https://api.github.com/users/stefansundin/subscriptions","organizations_url":"https://api.github.com/users/stefansundin/orgs","repos_url":"https://api.github.com/users/stefansundin/repos","events_url":"https://api.github.com/users/stefansundin/events{/privacy}","received_events_url":"https://api.github.com/users/stefansundin/received_events","type":"User","site_admin":false},"prerelease":true,"created_at":"2011-01-22T23:43:15Z","published_at":"2014-12-29T22:28:08Z","assets":[{"url":"https://api.github.com/repos/stefansundin/altdrag/releases/assets/359867","id":359867,"name":"AltDrag-0.9rc1.7z","label":null,"uploader":{"login":"stefansundin","id":1991151,"avatar_url":"https://avatars.githubusercontent.com/u/1991151?v=3","gravatar_id":"","url":"https://api.github.com/users/stefansundin","html_url":"https://github.com/stefansundin","followers_url":"https://api.github.com/users/stefansundin/followers","following_url":"https://api.github.com/users/stefansundin/following{/other_user}","gists_url":"https://api.github.com/users/stefansundin/gists{/gist_id}","starred_url":"https://api.github.com/users/stefansundin/starred{/owner}{/repo}","subscriptions_url":"https://api.github.com/users/stefansundin/subscriptions","organizations_url":"https://api.github.com/users/stefansundin/orgs","repos_url":"https://api.github.com/users/stefansundin/repos","events_url":"https://api.github.com/users/stefansundin/events{/privacy}","received_events_url":"https://api.github.com/users/stefansundin/received_events","type":"User","site_admin":false},"content_type":"application/octet-stream","state":"uploaded","size":38386,"download_count":2,"created_at":"2014-12-29T22:28:05Z","updated_at":"2014-12-29T22:28:07Z","browser_download_url":"https://github.com/stefansundin/altdrag/releases/download/v0.9rc1/AltDrag-0.9rc1.7z"}],"tarball_url":"https://api.github.com/repos/stefansundin/altdrag/tarball/v0.9rc1","zipball_url":"https://api.github.com/repos/stefansundin/altdrag/zipball/v0.9rc1","body":"2011-01-22:\r\n- Added `InactiveScroll`. Enable it to scroll inactive windows.\r\n- Fixed major bug with custom taskbar locations (only present in the beta).\r\n- Expanded `Aero` option.\r\n- Expanded `AutoRemaximized` option.\r\n- It is now possible to toggle the maximized state with a resize button while dragging."},{"url":"https://api.github.com/repos/stefansundin/altdrag/releases/814261","assets_url":"https://api.github.com/repos/stefansundin/altdrag/releases/814261/assets","upload_url":"https://uploads.github.com/repos/stefansundin/altdrag/releases/814261/assets{?name}","html_url":"https://github.com/stefansundin/altdrag/releases/tag/v0.9b1","id":814261,"tag_name":"v0.9b1","target_commitish":"master","name":"AltDrag v0.9b1","draft":false,"author":{"login":"stefansundin","id":1991151,"avatar_url":"https://avatars.githubusercontent.com/u/1991151?v=3","gravatar_id":"","url":"https://api.github.com/users/stefansundin","html_url":"https://github.com/stefansundin","followers_url":"https://api.github.com/users/stefansundin/followers","following_url":"https://api.github.com/users/stefansundin/following{/other_user}","gists_url":"https://api.github.com/users/stefansundin/gists{/gist_id}","starred_url":"https://api.github.com/users/stefansundin/starred{/owner}{/repo}","subscriptions_url":"https://api.github.com/users/stefansundin/subscriptions","organizations_url":"https://api.github.com/users/stefansundin/orgs","repos_url":"https://api.github.com/users/stefansundin/repos","events_url":"https://api.github.com/users/stefansundin/events{/privacy}","received_events_url":"https://api.github.com/users/stefansundin/received_events","type":"User","site_admin":false},"prerelease":true,"created_at":"2010-12-23T18:10:10Z","published_at":"2014-12-30T20:27:25Z","assets":[{"url":"https://api.github.com/repos/stefansundin/altdrag/releases/assets/359865","id":359865,"name":"AltDrag-0.9b1.7z","label":null,"uploader":{"login":"stefansundin","id":1991151,"avatar_url":"https://avatars.githubusercontent.com/u/1991151?v=3","gravatar_id":"","url":"https://api.github.com/users/stefansundin","html_url":"https://github.com/stefansundin","followers_url":"https://api.github.com/users/stefansundin/followers","following_url":"https://api.github.com/users/stefansundin/following{/other_user}","gists_url":"https://api.github.com/users/stefansundin/gists{/gist_id}","starred_url":"https://api.github.com/users/stefansundin/starred{/owner}{/repo}","subscriptions_url":"https://api.github.com/users/stefansundin/subscriptions","organizations_url":"https://api.github.com/users/stefansundin/orgs","repos_url":"https://api.github.com/users/stefansundin/repos","events_url":"https://api.github.com/users/stefansundin/events{/privacy}","received_events_url":"https://api.github.com/users/stefansundin/received_events","type":"User","site_admin":false},"content_type":"application/octet-stream","state":"uploaded","size":37821,"download_count":2,"created_at":"2014-12-29T22:27:07Z","updated_at":"2014-12-29T22:27:10Z","browser_download_url":"https://github.com/stefansundin/altdrag/releases/download/v0.9b1/AltDrag-0.9b1.7z"}],"tarball_url":"https://api.github.com/repos/stefansundin/altdrag/tarball/v0.9b1","zipball_url":"https://api.github.com/repos/stefansundin/altdrag/zipball/v0.9b1","body":"2010-12-23:\r\n- Added `Aero` option. Alt-drag windows to the left, right and top side of the screen. Corners work too!\r\n- Added new mouse actions: `AlwaysOnTop` and `Close`.\r\n- Replaced roll-up behavior with `Aero` behavior. Double-click with middle/right mouse button.\r\n- Renamed \"stick\" to \"snap\" as people seem to \"get\" that term better.\r\n- Fixed some bugs that prevented `HookWindows` from working properly.\r\n- Tweaked the blacklist."},{"url":"https://api.github.com/repos/stefansundin/altdrag/releases/314195","assets_url":"https://api.github.com/repos/stefansundin/altdrag/releases/314195/assets","upload_url":"https://uploads.github.com/repos/stefansundin/altdrag/releases/314195/assets{?name}","html_url":"https://github.com/stefansundin/altdrag/releases/tag/v1.0","id":314195,"tag_name":"v1.0","target_commitish":"master","name":"AltDrag v1.0","draft":false,"author":{"login":"stefansundin","id":1991151,"avatar_url":"https://avatars.githubusercontent.com/u/1991151?v=3","gravatar_id":"","url":"https://api.github.com/users/stefansundin","html_url":"https://github.com/stefansundin","followers_url":"https://api.github.com/users/stefansundin/followers","following_url":"https://api.github.com/users/stefansundin/following{/other_user}","gists_url":"https://api.github.com/users/stefansundin/gists{/gist_id}","starred_url":"https://api.github.com/users/stefansundin/starred{/owner}{/repo}","subscriptions_url":"https://api.github.com/users/stefansundin/subscriptions","organizations_url":"https://api.github.com/users/stefansundin/orgs","repos_url":"https://api.github.com/users/stefansundin/repos","events_url":"https://api.github.com/users/stefansundin/events{/privacy}","received_events_url":"https://api.github.com/users/stefansundin/received_events","type":"User","site_admin":false},"prerelease":false,"created_at":"2013-09-13T11:36:48Z","published_at":"2014-05-11T05:05:11Z","assets":[{"url":"https://api.github.com/repos/stefansundin/altdrag/releases/assets/132892","id":132892,"name":"AltDrag-1.0.7z","label":"","uploader":{"login":"stefansundin","id":1991151,"avatar_url":"https://avatars.githubusercontent.com/u/1991151?v=3","gravatar_id":"","url":"https://api.github.com/users/stefansundin","html_url":"https://github.com/stefansundin","followers_url":"https://api.github.com/users/stefansundin/followers","following_url":"https://api.github.com/users/stefansundin/following{/other_user}","gists_url":"https://api.github.com/users/stefansundin/gists{/gist_id}","starred_url":"https://api.github.com/users/stefansundin/starred{/owner}{/repo}","subscriptions_url":"https://api.github.com/users/stefansundin/subscriptions","organizations_url":"https://api.github.com/users/stefansundin/orgs","repos_url":"https://api.github.com/users/stefansundin/repos","events_url":"https://api.github.com/users/stefansundin/events{/privacy}","received_events_url":"https://api.github.com/users/stefansundin/received_events","type":"User","site_admin":false},"content_type":"application/octet-stream","state":"uploaded","size":62655,"download_count":1925,"created_at":"2014-05-11T05:05:06Z","updated_at":"2014-05-11T05:05:11Z","browser_download_url":"https://github.com/stefansundin/altdrag/releases/download/v1.0/AltDrag-1.0.7z"},{"url":"https://api.github.com/repos/stefansundin/altdrag/releases/assets/132893","id":132893,"name":"AltDrag-1.0.exe","label":"","uploader":{"login":"stefansundin","id":1991151,"avatar_url":"https://avatars.githubusercontent.com/u/1991151?v=3","gravatar_id":"","url":"https://api.github.com/users/stefansundin","html_url":"https://github.com/stefansundin","followers_url":"https://api.github.com/users/stefansundin/followers","following_url":"https://api.github.com/users/stefansundin/following{/other_user}","gists_url":"https://api.github.com/users/stefansundin/gists{/gist_id}","starred_url":"https://api.github.com/users/stefansundin/starred{/owner}{/repo}","subscriptions_url":"https://api.github.com/users/stefansundin/subscriptions","organizations_url":"https://api.github.com/users/stefansundin/orgs","repos_url":"https://api.github.com/users/stefansundin/repos","events_url":"https://api.github.com/users/stefansundin/events{/privacy}","received_events_url":"https://api.github.com/users/stefansundin/received_events","type":"User","site_admin":false},"content_type":"application/x-msdownload","state":"uploaded","size":193813,"download_count":8560,"created_at":"2014-05-11T05:05:07Z","updated_at":"2014-05-11T05:05:11Z","browser_download_url":"https://github.com/stefansundin/altdrag/releases/download/v1.0/AltDrag-1.0.exe"}],"tarball_url":"https://api.github.com/repos/stefansundin/altdrag/tarball/v1.0","zipball_url":"https://api.github.com/repos/stefansundin/altdrag/zipball/v1.0","body":"[Get RSS updates by monitoring the release feed.](https://github.com/stefansundin/altdrag/releases.atom)\r\n\r\n**final** - 2013-09-13:\r\n- Add `Lower` scroll wheel action. Scroll down to lower windows, scroll up to raise windows, shift+scroll down to minimize windows, shift+scroll up to toggle maximized state.\r\n- Other `Lower` actions will now also minimize the window if you hold shift.\r\n- Updated most of the translations.\r\n\r\n**release candidate** - 2013-09-06:\r\n- Add support for MDI windows. Works with many features (e.g. `HookWindows`, `AltTab` scrolling, snapping).\r\n- Add ability to lower windows by middle clicking title bars.\r\n- Add ability to translate AltDrag with an ini file.\r\n- Many small fixes for multiple monitors.\r\n- Made the corner regions for resizing bigger, now corners are 38% and middle regions 24%. Before all regions were 33%.\r\n- Fixed `HookWindows` sometimes blocking the space key.\r\n- Fixed a few issues with `InactiveScroll`.\r\n\r\n**beta 3** - 2013-06-20:\r\n- If you enable `InactiveScroll`, you can now hold the shift key to scroll horizontally. Note that this only works in programs that have implemented horizontal scrolling.\r\n- New scroll action: `Transparency`. It allows you to set the transparency of arbitrary windows.\r\n- The code that prevents the window menu from triggering has been reworked to work with Internet Explorer.\r\n\r\n**beta 2** - 2013-04-20:\r\n- Merged `Config.exe` with `AltDrag.exe`.\r\n- Made it possible to disable the Alt+Scroll action. It was silly of me to not let you do this in beta 1, sorry!\r\n- Added new Alt+Scroll action that changes the volume.\r\n- You can now press the Space key during a drag to reset any custom `AutoSnap` setting for the duration of the drag.\r\n- AltDrag can now request elevation to administrator privileges on demand, allowing for much easier elevation on autostart.\r\n- AltDrag can now be run in multiple instances, useful if you e.g. want to use Alt+LMB to move and Ctrl+LMB to resize. See `MultipleInstances` in the ini file.\r\n- Added experimental feature `FocusOnTyping` that moves focus to the window the mouse is hovering when you start typing. This is a new approach to the hidden X-Mouse feature in Windows. See the ini file for more details.\r\n- Fixed issue with iTunes.\r\n\r\n**beta 1** - 2011-07-31:\r\n- Added configuration GUI.\r\n- Added ability to scroll through windows with the scrollwheel (like Alt+Tab!).\r\n- Added ability to blacklist by process name.\r\n- Added new mouse action: `Lower`.\r\n- Added performance options `MoveRate` and `ResizeRate`. Increase if dragging or resizing is slow.\r\n- The scroll hook should no longer stop working when locking the screen or resuming the computer from sleep. A timer checks every 5 seconds if the scroll hook is still working, and re-enables it if it is not.\r\n- You can now press Escape to stop AltDrag. Useful if AltDrag gets in a weird state.\r\n- You can now press Ctrl to make AltDrag think the mouse cursor is still inside the current monitor. Should help people who have multiple monitors and want to snap at borders between monitors.\r\n- Installer now grants access to `AltDrag.ini` to all users. Should help people who use UAC.\r\n- Removed `info.txt`. Use the website for help."},{"url":"https://api.github.com/repos/stefansundin/altdrag/releases/314194","assets_url":"https://api.github.com/repos/stefansundin/altdrag/releases/314194/assets","upload_url":"https://uploads.github.com/repos/stefansundin/altdrag/releases/314194/assets{?name}","html_url":"https://github.com/stefansundin/altdrag/releases/tag/v0.9","id":314194,"tag_name":"v0.9","target_commitish":"master","name":"AltDrag v0.9","draft":false,"author":{"login":"stefansundin","id":1991151,"avatar_url":"https://avatars.githubusercontent.com/u/1991151?v=3","gravatar_id":"","url":"https://api.github.com/users/stefansundin","html_url":"https://github.com/stefansundin","followers_url":"https://api.github.com/users/stefansundin/followers","following_url":"https://api.github.com/users/stefansundin/following{/other_user}","gists_url":"https://api.github.com/users/stefansundin/gists{/gist_id}","starred_url":"https://api.github.com/users/stefansundin/starred{/owner}{/repo}","subscriptions_url":"https://api.github.com/users/stefansundin/subscriptions","organizations_url":"https://api.github.com/users/stefansundin/orgs","repos_url":"https://api.github.com/users/stefansundin/repos","events_url":"https://api.github.com/users/stefansundin/events{/privacy}","received_events_url":"https://api.github.com/users/stefansundin/received_events","type":"User","site_admin":false},"prerelease":false,"created_at":"2011-02-01T19:22:58Z","published_at":"2014-05-11T05:04:41Z","assets":[{"url":"https://api.github.com/repos/stefansundin/altdrag/releases/assets/132890","id":132890,"name":"AltDrag-0.9.7z","label":"","uploader":{"login":"stefansundin","id":1991151,"avatar_url":"https://avatars.githubusercontent.com/u/1991151?v=3","gravatar_id":"","url":"https://api.github.com/users/stefansundin","html_url":"https://github.com/stefansundin","followers_url":"https://api.github.com/users/stefansundin/followers","following_url":"https://api.github.com/users/stefansundin/following{/other_user}","gists_url":"https://api.github.com/users/stefansundin/gists{/gist_id}","starred_url":"https://api.github.com/users/stefansundin/starred{/owner}{/repo}","subscriptions_url":"https://api.github.com/users/stefansundin/subscriptions","organizations_url":"https://api.github.com/users/stefansundin/orgs","repos_url":"https://api.github.com/users/stefansundin/repos","events_url":"https://api.github.com/users/stefansundin/events{/privacy}","received_events_url":"https://api.github.com/users/stefansundin/received_events","type":"User","site_admin":false},"content_type":"application/octet-stream","state":"uploaded","size":38130,"download_count":3,"created_at":"2014-05-11T05:04:36Z","updated_at":"2014-05-11T05:04:41Z","browser_download_url":"https://github.com/stefansundin/altdrag/releases/download/v0.9/AltDrag-0.9.7z"},{"url":"https://api.github.com/repos/stefansundin/altdrag/releases/assets/132891","id":132891,"name":"AltDrag-0.9.exe","label":"","uploader":{"login":"stefansundin","id":1991151,"avatar_url":"https://avatars.githubusercontent.com/u/1991151?v=3","gravatar_id":"","url":"https://api.github.com/users/stefansundin","html_url":"https://github.com/stefansundin","followers_url":"https://api.github.com/users/stefansundin/followers","following_url":"https://api.github.com/users/stefansundin/following{/other_user}","gists_url":"https://api.github.com/users/stefansundin/gists{/gist_id}","starred_url":"https://api.github.com/users/stefansundin/starred{/owner}{/repo}","subscriptions_url":"https://api.github.com/users/stefansundin/subscriptions","organizations_url":"https://api.github.com/users/stefansundin/orgs","repos_url":"https://api.github.com/users/stefansundin/repos","events_url":"https://api.github.com/users/stefansundin/events{/privacy}","received_events_url":"https://api.github.com/users/stefansundin/received_events","type":"User","site_admin":false},"content_type":"application/x-msdownload","state":"uploaded","size":142288,"download_count":4,"created_at":"2014-05-11T05:04:38Z","updated_at":"2014-05-11T05:04:41Z","browser_download_url":"https://github.com/stefansundin/altdrag/releases/download/v0.9/AltDrag-0.9.exe"}],"tarball_url":"https://api.github.com/repos/stefansundin/altdrag/tarball/v0.9","zipball_url":"https://api.github.com/repos/stefansundin/altdrag/zipball/v0.9","body":"2011-02-01:\r\n- Added `Aero` option. Alt-drag windows to the left, right and top side of the screen. Corners work too!\r\n- Added `AutoFocus` and `AutoRemaximize` options.\r\n- Added `InactiveScroll`. Enable it to scroll inactive windows.\r\n- Added new mouse actions: `AlwaysOnTop` and `Close`.\r\n- It is now possible to toggle the maximized state with a resize button while dragging.\r\n- Replaced roll-up behavior with Aero behavior.\r\n- Renamed \"stick\" to \"snap\" as people seem to \"get\" that term better.\r\n- Fixed some bugs that prevented `HookWindows` from working properly.\r\n- Tweaked the blacklist."},{"url":"https://api.github.com/repos/stefansundin/altdrag/releases/314193","assets_url":"https://api.github.com/repos/stefansundin/altdrag/releases/314193/assets","upload_url":"https://uploads.github.com/repos/stefansundin/altdrag/releases/314193/assets{?name}","html_url":"https://github.com/stefansundin/altdrag/releases/tag/v0.8","id":314193,"tag_name":"v0.8","target_commitish":"master","name":"AltDrag v0.8","draft":false,"author":{"login":"stefansundin","id":1991151,"avatar_url":"https://avatars.githubusercontent.com/u/1991151?v=3","gravatar_id":"","url":"https://api.github.com/users/stefansundin","html_url":"https://github.com/stefansundin","followers_url":"https://api.github.com/users/stefansundin/followers","following_url":"https://api.github.com/users/stefansundin/following{/other_user}","gists_url":"https://api.github.com/users/stefansundin/gists{/gist_id}","starred_url":"https://api.github.com/users/stefansundin/starred{/owner}{/repo}","subscriptions_url":"https://api.github.com/users/stefansundin/subscriptions","organizations_url":"https://api.github.com/users/stefansundin/orgs","repos_url":"https://api.github.com/users/stefansundin/repos","events_url":"https://api.github.com/users/stefansundin/events{/privacy}","received_events_url":"https://api.github.com/users/stefansundin/received_events","type":"User","site_admin":false},"prerelease":false,"created_at":"2009-11-15T19:52:43Z","published_at":"2014-05-11T05:04:12Z","assets":[{"url":"https://api.github.com/repos/stefansundin/altdrag/releases/assets/132888","id":132888,"name":"AltDrag-0.8.7z","label":"","uploader":{"login":"stefansundin","id":1991151,"avatar_url":"https://avatars.githubusercontent.com/u/1991151?v=3","gravatar_id":"","url":"https://api.github.com/users/stefansundin","html_url":"https://github.com/stefansundin","followers_url":"https://api.github.com/users/stefansundin/followers","following_url":"https://api.github.com/users/stefansundin/following{/other_user}","gists_url":"https://api.github.com/users/stefansundin/gists{/gist_id}","starred_url":"https://api.github.com/users/stefansundin/starred{/owner}{/repo}","subscriptions_url":"https://api.github.com/users/stefansundin/subscriptions","organizations_url":"https://api.github.com/users/stefansundin/orgs","repos_url":"https://api.github.com/users/stefansundin/repos","events_url":"https://api.github.com/users/stefansundin/events{/privacy}","received_events_url":"https://api.github.com/users/stefansundin/received_events","type":"User","site_admin":false},"content_type":"application/octet-stream","state":"uploaded","size":34150,"download_count":3,"created_at":"2014-05-11T05:04:07Z","updated_at":"2014-05-11T05:04:12Z","browser_download_url":"https://github.com/stefansundin/altdrag/releases/download/v0.8/AltDrag-0.8.7z"},{"url":"https://api.github.com/repos/stefansundin/altdrag/releases/assets/132889","id":132889,"name":"AltDrag-0.8.exe","label":"","uploader":{"login":"stefansundin","id":1991151,"avatar_url":"https://avatars.githubusercontent.com/u/1991151?v=3","gravatar_id":"","url":"https://api.github.com/users/stefansundin","html_url":"https://github.com/stefansundin","followers_url":"https://api.github.com/users/stefansundin/followers","following_url":"https://api.github.com/users/stefansundin/following{/other_user}","gists_url":"https://api.github.com/users/stefansundin/gists{/gist_id}","starred_url":"https://api.github.com/users/stefansundin/starred{/owner}{/repo}","subscriptions_url":"https://api.github.com/users/stefansundin/subscriptions","organizations_url":"https://api.github.com/users/stefansundin/orgs","repos_url":"https://api.github.com/users/stefansundin/repos","events_url":"https://api.github.com/users/stefansundin/events{/privacy}","received_events_url":"https://api.github.com/users/stefansundin/received_events","type":"User","site_admin":false},"content_type":"application/x-msdownload","state":"uploaded","size":148426,"download_count":7,"created_at":"2014-05-11T05:04:09Z","updated_at":"2014-05-11T05:04:12Z","browser_download_url":"https://github.com/stefansundin/altdrag/releases/download/v0.8/AltDrag-0.8.exe"}],"tarball_url":"https://api.github.com/repos/stefansundin/altdrag/tarball/v0.8","zipball_url":"https://api.github.com/repos/stefansundin/altdrag/zipball/v0.8","body":"2009-11-15:\r\n- Added `AutoStick`, enable it to make windows always stick without needing to press shift. This replaces `StickyScreen`.\r\n- Renamed `ExperimentalFeatures` to `HookWindows`, also improved it so resizing is now supported and windows should no longer flicker. 64-bit programs also work now. I no longer consider it experimental!\r\n- The alt key will no longer activate the window menu!\r\n- Added the ability to configure what keys should trigger the dragging, resizing, etc.\r\n- Added the ability to configure what the mouse buttons do. New actions: minimize and center.\r\n- Improved multi-monitor support a lot.\r\n- Tweaked the blacklist."},{"url":"https://api.github.com/repos/stefansundin/altdrag/releases/314191","assets_url":"https://api.github.com/repos/stefansundin/altdrag/releases/314191/assets","upload_url":"https://uploads.github.com/repos/stefansundin/altdrag/releases/314191/assets{?name}","html_url":"https://github.com/stefansundin/altdrag/releases/tag/v0.7","id":314191,"tag_name":"v0.7","target_commitish":"master","name":"AltDrag v0.7","draft":false,"author":{"login":"stefansundin","id":1991151,"avatar_url":"https://avatars.githubusercontent.com/u/1991151?v=3","gravatar_id":"","url":"https://api.github.com/users/stefansundin","html_url":"https://github.com/stefansundin","followers_url":"https://api.github.com/users/stefansundin/followers","following_url":"https://api.github.com/users/stefansundin/following{/other_user}","gists_url":"https://api.github.com/users/stefansundin/gists{/gist_id}","starred_url":"https://api.github.com/users/stefansundin/starred{/owner}{/repo}","subscriptions_url":"https://api.github.com/users/stefansundin/subscriptions","organizations_url":"https://api.github.com/users/stefansundin/orgs","repos_url":"https://api.github.com/users/stefansundin/repos","events_url":"https://api.github.com/users/stefansundin/events{/privacy}","received_events_url":"https://api.github.com/users/stefansundin/received_events","type":"User","site_admin":false},"prerelease":false,"created_at":"2009-04-24T17:10:10Z","published_at":"2014-12-30T20:19:33Z","assets":[{"url":"https://api.github.com/repos/stefansundin/altdrag/releases/assets/132885","id":132885,"name":"AltDrag-0.7.7z","label":"","uploader":{"login":"stefansundin","id":1991151,"avatar_url":"https://avatars.githubusercontent.com/u/1991151?v=3","gravatar_id":"","url":"https://api.github.com/users/stefansundin","html_url":"https://github.com/stefansundin","followers_url":"https://api.github.com/users/stefansundin/followers","following_url":"https://api.github.com/users/stefansundin/following{/other_user}","gists_url":"https://api.github.com/users/stefansundin/gists{/gist_id}","starred_url":"https://api.github.com/users/stefansundin/starred{/owner}{/repo}","subscriptions_url":"https://api.github.com/users/stefansundin/subscriptions","organizations_url":"https://api.github.com/users/stefansundin/orgs","repos_url":"https://api.github.com/users/stefansundin/repos","events_url":"https://api.github.com/users/stefansundin/events{/privacy}","received_events_url":"https://api.github.com/users/stefansundin/received_events","type":"User","site_admin":false},"content_type":"application/octet-stream","state":"uploaded","size":16000,"download_count":3,"created_at":"2014-05-11T05:01:36Z","updated_at":"2014-05-11T05:01:42Z","browser_download_url":"https://github.com/stefansundin/altdrag/releases/download/v0.7/AltDrag-0.7.7z"},{"url":"https://api.github.com/repos/stefansundin/altdrag/releases/assets/132886","id":132886,"name":"AltDrag-0.7.exe","label":"","uploader":{"login":"stefansundin","id":1991151,"avatar_url":"https://avatars.githubusercontent.com/u/1991151?v=3","gravatar_id":"","url":"https://api.github.com/users/stefansundin","html_url":"https://github.com/stefansundin","followers_url":"https://api.github.com/users/stefansundin/followers","following_url":"https://api.github.com/users/stefansundin/following{/other_user}","gists_url":"https://api.github.com/users/stefansundin/gists{/gist_id}","starred_url":"https://api.github.com/users/stefansundin/starred{/owner}{/repo}","subscriptions_url":"https://api.github.com/users/stefansundin/subscriptions","organizations_url":"https://api.github.com/users/stefansundin/orgs","repos_url":"https://api.github.com/users/stefansundin/repos","events_url":"https://api.github.com/users/stefansundin/events{/privacy}","received_events_url":"https://api.github.com/users/stefansundin/received_events","type":"User","site_admin":false},"content_type":"application/x-msdownload","state":"uploaded","size":121353,"download_count":5,"created_at":"2014-05-11T05:01:38Z","updated_at":"2014-05-11T05:01:42Z","browser_download_url":"https://github.com/stefansundin/altdrag/releases/download/v0.7/AltDrag-0.7.exe"}],"tarball_url":"https://api.github.com/repos/stefansundin/altdrag/tarball/v0.7","zipball_url":"https://api.github.com/repos/stefansundin/altdrag/zipball/v0.7","body":"2009-04-24:\r\n- Added `StickyScreen` which makes windows automatically stick to the screen borders without needing shift (off by default).\r\n- Added the ability to roll-up windows by double-clicking with the middle mouse button.\r\n- Fixed some bugs in `ExperimentalFeatures`, it's working pretty well now so give it a try.\r\n- Fixed an annoying error message that sometimes popped up when AltDrag was on autostart."},{"url":"https://api.github.com/repos/stefansundin/altdrag/releases/314190","assets_url":"https://api.github.com/repos/stefansundin/altdrag/releases/314190/assets","upload_url":"https://uploads.github.com/repos/stefansundin/altdrag/releases/314190/assets{?name}","html_url":"https://github.com/stefansundin/altdrag/releases/tag/v0.6","id":314190,"tag_name":"v0.6","target_commitish":"master","name":"AltDrag v0.6","draft":false,"author":{"login":"stefansundin","id":1991151,"avatar_url":"https://avatars.githubusercontent.com/u/1991151?v=3","gravatar_id":"","url":"https://api.github.com/users/stefansundin","html_url":"https://github.com/stefansundin","followers_url":"https://api.github.com/users/stefansundin/followers","following_url":"https://api.github.com/users/stefansundin/following{/other_user}","gists_url":"https://api.github.com/users/stefansundin/gists{/gist_id}","starred_url":"https://api.github.com/users/stefansundin/starred{/owner}{/repo}","subscriptions_url":"https://api.github.com/users/stefansundin/subscriptions","organizations_url":"https://api.github.com/users/stefansundin/orgs","repos_url":"https://api.github.com/users/stefansundin/repos","events_url":"https://api.github.com/users/stefansundin/events{/privacy}","received_events_url":"https://api.github.com/users/stefansundin/received_events","type":"User","site_admin":false},"prerelease":false,"created_at":"2009-02-12T20:11:24Z","published_at":"2014-05-11T05:01:15Z","assets":[{"url":"https://api.github.com/repos/stefansundin/altdrag/releases/assets/132883","id":132883,"name":"AltDrag-0.6.7z","label":"","uploader":{"login":"stefansundin","id":1991151,"avatar_url":"https://avatars.githubusercontent.com/u/1991151?v=3","gravatar_id":"","url":"https://api.github.com/users/stefansundin","html_url":"https://github.com/stefansundin","followers_url":"https://api.github.com/users/stefansundin/followers","following_url":"https://api.github.com/users/stefansundin/following{/other_user}","gists_url":"https://api.github.com/users/stefansundin/gists{/gist_id}","starred_url":"https://api.github.com/users/stefansundin/starred{/owner}{/repo}","subscriptions_url":"https://api.github.com/users/stefansundin/subscriptions","organizations_url":"https://api.github.com/users/stefansundin/orgs","repos_url":"https://api.github.com/users/stefansundin/repos","events_url":"https://api.github.com/users/stefansundin/events{/privacy}","received_events_url":"https://api.github.com/users/stefansundin/received_events","type":"User","site_admin":false},"content_type":"application/octet-stream","state":"uploaded","size":14845,"download_count":3,"created_at":"2014-05-11T05:01:10Z","updated_at":"2014-05-11T05:01:15Z","browser_download_url":"https://github.com/stefansundin/altdrag/releases/download/v0.6/AltDrag-0.6.7z"},{"url":"https://api.github.com/repos/stefansundin/altdrag/releases/assets/132884","id":132884,"name":"AltDrag-0.6.exe","label":"","uploader":{"login":"stefansundin","id":1991151,"avatar_url":"https://avatars.githubusercontent.com/u/1991151?v=3","gravatar_id":"","url":"https://api.github.com/users/stefansundin","html_url":"https://github.com/stefansundin","followers_url":"https://api.github.com/users/stefansundin/followers","following_url":"https://api.github.com/users/stefansundin/following{/other_user}","gists_url":"https://api.github.com/users/stefansundin/gists{/gist_id}","starred_url":"https://api.github.com/users/stefansundin/starred{/owner}{/repo}","subscriptions_url":"https://api.github.com/users/stefansundin/subscriptions","organizations_url":"https://api.github.com/users/stefansundin/orgs","repos_url":"https://api.github.com/users/stefansundin/repos","events_url":"https://api.github.com/users/stefansundin/events{/privacy}","received_events_url":"https://api.github.com/users/stefansundin/received_events","type":"User","site_admin":false},"content_type":"application/x-msdownload","state":"uploaded","size":113313,"download_count":4,"created_at":"2014-05-11T05:01:12Z","updated_at":"2014-05-11T05:01:15Z","browser_download_url":"https://github.com/stefansundin/altdrag/releases/download/v0.6/AltDrag-0.6.exe"}],"tarball_url":"https://api.github.com/repos/stefansundin/altdrag/tarball/v0.6","zipball_url":"https://api.github.com/repos/stefansundin/altdrag/zipball/v0.6","body":"2009-02-12:\r\n- Sticky behavior now works with resize (except when resizing in all directions).\r\n- Fixed tray not being hidden by `-hide`.\r\n- Fixed mouse cursor not changing when Aero was disabled in Vista.\r\n- Language can now be changed in `AltDrag.ini`."},{"url":"https://api.github.com/repos/stefansundin/altdrag/releases/314189","assets_url":"https://api.github.com/repos/stefansundin/altdrag/releases/314189/assets","upload_url":"https://uploads.github.com/repos/stefansundin/altdrag/releases/314189/assets{?name}","html_url":"https://github.com/stefansundin/altdrag/releases/tag/v0.5","id":314189,"tag_name":"v0.5","target_commitish":"master","name":"AltDrag v0.5","draft":false,"author":{"login":"stefansundin","id":1991151,"avatar_url":"https://avatars.githubusercontent.com/u/1991151?v=3","gravatar_id":"","url":"https://api.github.com/users/stefansundin","html_url":"https://github.com/stefansundin","followers_url":"https://api.github.com/users/stefansundin/followers","following_url":"https://api.github.com/users/stefansundin/following{/other_user}","gists_url":"https://api.github.com/users/stefansundin/gists{/gist_id}","starred_url":"https://api.github.com/users/stefansundin/starred{/owner}{/repo}","subscriptions_url":"https://api.github.com/users/stefansundin/subscriptions","organizations_url":"https://api.github.com/users/stefansundin/orgs","repos_url":"https://api.github.com/users/stefansundin/repos","events_url":"https://api.github.com/users/stefansundin/events{/privacy}","received_events_url":"https://api.github.com/users/stefansundin/received_events","type":"User","site_admin":false},"prerelease":false,"created_at":"2009-01-13T14:22:57Z","published_at":"2014-05-11T04:58:08Z","assets":[{"url":"https://api.github.com/repos/stefansundin/altdrag/releases/assets/132881","id":132881,"name":"AltDrag-0.5.7z","label":"","uploader":{"login":"stefansundin","id":1991151,"avatar_url":"https://avatars.githubusercontent.com/u/1991151?v=3","gravatar_id":"","url":"https://api.github.com/users/stefansundin","html_url":"https://github.com/stefansundin","followers_url":"https://api.github.com/users/stefansundin/followers","following_url":"https://api.github.com/users/stefansundin/following{/other_user}","gists_url":"https://api.github.com/users/stefansundin/gists{/gist_id}","starred_url":"https://api.github.com/users/stefansundin/starred{/owner}{/repo}","subscriptions_url":"https://api.github.com/users/stefansundin/subscriptions","organizations_url":"https://api.github.com/users/stefansundin/orgs","repos_url":"https://api.github.com/users/stefansundin/repos","events_url":"https://api.github.com/users/stefansundin/events{/privacy}","received_events_url":"https://api.github.com/users/stefansundin/received_events","type":"User","site_admin":false},"content_type":"application/octet-stream","state":"uploaded","size":15428,"download_count":3,"created_at":"2014-05-11T04:58:03Z","updated_at":"2014-05-11T04:58:08Z","browser_download_url":"https://github.com/stefansundin/altdrag/releases/download/v0.5/AltDrag-0.5.7z"},{"url":"https://api.github.com/repos/stefansundin/altdrag/releases/assets/132882","id":132882,"name":"AltDrag-0.5.exe","label":"","uploader":{"login":"stefansundin","id":1991151,"avatar_url":"https://avatars.githubusercontent.com/u/1991151?v=3","gravatar_id":"","url":"https://api.github.com/users/stefansundin","html_url":"https://github.com/stefansundin","followers_url":"https://api.github.com/users/stefansundin/followers","following_url":"https://api.github.com/users/stefansundin/following{/other_user}","gists_url":"https://api.github.com/users/stefansundin/gists{/gist_id}","starred_url":"https://api.github.com/users/stefansundin/starred{/owner}{/repo}","subscriptions_url":"https://api.github.com/users/stefansundin/subscriptions","organizations_url":"https://api.github.com/users/stefansundin/orgs","repos_url":"https://api.github.com/users/stefansundin/repos","events_url":"https://api.github.com/users/stefansundin/events{/privacy}","received_events_url":"https://api.github.com/users/stefansundin/received_events","type":"User","site_admin":false},"content_type":"application/x-msdownload","state":"uploaded","size":126137,"download_count":4,"created_at":"2014-05-11T04:58:05Z","updated_at":"2014-05-11T05:00:50Z","browser_download_url":"https://github.com/stefansundin/altdrag/releases/download/v0.5/AltDrag-0.5.exe"}],"tarball_url":"https://api.github.com/repos/stefansundin/altdrag/tarball/v0.5","zipball_url":"https://api.github.com/repos/stefansundin/altdrag/zipball/v0.5","body":"2009-01-12:\r\n- You can now resize windows with the middle or right mouse button.\r\n- You can now double-click a window to maximize it.\r\n- You can now blacklist certain windows from being dragged and certain windows from being sticked to.\r\n- Blacklisted by default: the alt+tab window in Vista.\r\n- Sticky-blacklisted by default: the Vista start menu orb.\r\n- The mouse cursor will now change when you move and resize windows.\r\n- Only one instance of AltDrag can now be run. Starting AltDrag again will make the first copy add its tray icon.\r\n- Experimental feature disabled by default: you can now press the shift key while normally moving windows (dragging the titlebar) to make them stick. Doesn't work on all windows in Vista. Doesn't work with 64-bit processes."},{"url":"https://api.github.com/repos/stefansundin/altdrag/releases/314188","assets_url":"https://api.github.com/repos/stefansundin/altdrag/releases/314188/assets","upload_url":"https://uploads.github.com/repos/stefansundin/altdrag/releases/314188/assets{?name}","html_url":"https://github.com/stefansundin/altdrag/releases/tag/v0.4","id":314188,"tag_name":"v0.4","target_commitish":"master","name":"AltDrag v0.4","draft":false,"author":{"login":"stefansundin","id":1991151,"avatar_url":"https://avatars.githubusercontent.com/u/1991151?v=3","gravatar_id":"","url":"https://api.github.com/users/stefansundin","html_url":"https://github.com/stefansundin","followers_url":"https://api.github.com/users/stefansundin/followers","following_url":"https://api.github.com/users/stefansundin/following{/other_user}","gists_url":"https://api.github.com/users/stefansundin/gists{/gist_id}","starred_url":"https://api.github.com/users/stefansundin/starred{/owner}{/repo}","subscriptions_url":"https://api.github.com/users/stefansundin/subscriptions","organizations_url":"https://api.github.com/users/stefansundin/orgs","repos_url":"https://api.github.com/users/stefansundin/repos","events_url":"https://api.github.com/users/stefansundin/events{/privacy}","received_events_url":"https://api.github.com/users/stefansundin/received_events","type":"User","site_admin":false},"prerelease":false,"created_at":"2008-09-14T17:10:10Z","published_at":"2014-12-30T20:21:18Z","assets":[{"url":"https://api.github.com/repos/stefansundin/altdrag/releases/assets/132880","id":132880,"name":"AltDrag-0.4.7z","label":"","uploader":{"login":"stefansundin","id":1991151,"avatar_url":"https://avatars.githubusercontent.com/u/1991151?v=3","gravatar_id":"","url":"https://api.github.com/users/stefansundin","html_url":"https://github.com/stefansundin","followers_url":"https://api.github.com/users/stefansundin/followers","following_url":"https://api.github.com/users/stefansundin/following{/other_user}","gists_url":"https://api.github.com/users/stefansundin/gists{/gist_id}","starred_url":"https://api.github.com/users/stefansundin/starred{/owner}{/repo}","subscriptions_url":"https://api.github.com/users/stefansundin/subscriptions","organizations_url":"https://api.github.com/users/stefansundin/orgs","repos_url":"https://api.github.com/users/stefansundin/repos","events_url":"https://api.github.com/users/stefansundin/events{/privacy}","received_events_url":"https://api.github.com/users/stefansundin/received_events","type":"User","site_admin":false},"content_type":"application/octet-stream","state":"uploaded","size":10275,"download_count":3,"created_at":"2014-05-11T04:57:35Z","updated_at":"2014-05-11T04:57:37Z","browser_download_url":"https://github.com/stefansundin/altdrag/releases/download/v0.4/AltDrag-0.4.7z"}],"tarball_url":"https://api.github.com/repos/stefansundin/altdrag/tarball/v0.4","zipball_url":"https://api.github.com/repos/stefansundin/altdrag/zipball/v0.4","body":"2008-09-14:\r\n- You can now press the shift key to make the window stick to other windows."},{"url":"https://api.github.com/repos/stefansundin/altdrag/releases/314187","assets_url":"https://api.github.com/repos/stefansundin/altdrag/releases/314187/assets","upload_url":"https://uploads.github.com/repos/stefansundin/altdrag/releases/314187/assets{?name}","html_url":"https://github.com/stefansundin/altdrag/releases/tag/v0.3","id":314187,"tag_name":"v0.3","target_commitish":"master","name":"AltDrag v0.3","draft":false,"author":{"login":"stefansundin","id":1991151,"avatar_url":"https://avatars.githubusercontent.com/u/1991151?v=3","gravatar_id":"","url":"https://api.github.com/users/stefansundin","html_url":"https://github.com/stefansundin","followers_url":"https://api.github.com/users/stefansundin/followers","following_url":"https://api.github.com/users/stefansundin/following{/other_user}","gists_url":"https://api.github.com/users/stefansundin/gists{/gist_id}","starred_url":"https://api.github.com/users/stefansundin/starred{/owner}{/repo}","subscriptions_url":"https://api.github.com/users/stefansundin/subscriptions","organizations_url":"https://api.github.com/users/stefansundin/orgs","repos_url":"https://api.github.com/users/stefansundin/repos","events_url":"https://api.github.com/users/stefansundin/events{/privacy}","received_events_url":"https://api.github.com/users/stefansundin/received_events","type":"User","site_admin":false},"prerelease":false,"created_at":"2008-08-03T17:10:10Z","published_at":"2014-12-30T20:24:43Z","assets":[{"url":"https://api.github.com/repos/stefansundin/altdrag/releases/assets/132879","id":132879,"name":"AltDrag-0.3.7z","label":"","uploader":{"login":"stefansundin","id":1991151,"avatar_url":"https://avatars.githubusercontent.com/u/1991151?v=3","gravatar_id":"","url":"https://api.github.com/users/stefansundin","html_url":"https://github.com/stefansundin","followers_url":"https://api.github.com/users/stefansundin/followers","following_url":"https://api.github.com/users/stefansundin/following{/other_user}","gists_url":"https://api.github.com/users/stefansundin/gists{/gist_id}","starred_url":"https://api.github.com/users/stefansundin/starred{/owner}{/repo}","subscriptions_url":"https://api.github.com/users/stefansundin/subscriptions","organizations_url":"https://api.github.com/users/stefansundin/orgs","repos_url":"https://api.github.com/users/stefansundin/repos","events_url":"https://api.github.com/users/stefansundin/events{/privacy}","received_events_url":"https://api.github.com/users/stefansundin/received_events","type":"User","site_admin":false},"content_type":"application/octet-stream","state":"uploaded","size":9776,"download_count":3,"created_at":"2014-05-11T04:57:16Z","updated_at":"2014-05-11T04:57:17Z","browser_download_url":"https://github.com/stefansundin/altdrag/releases/download/v0.3/AltDrag-0.3.7z"}],"tarball_url":"https://api.github.com/repos/stefansundin/altdrag/tarball/v0.3","zipball_url":"https://api.github.com/repos/stefansundin/altdrag/zipball/v0.3","body":"2008-08-03:\r\n- Fixed a bug that made AltDrag ignore all windows which were at the screen borders since it thought they were fullscreen windows.\r\n- Improved performance by only installing the mouse hook when the alt key is pressed.\r\n"},{"url":"https://api.github.com/repos/stefansundin/altdrag/releases/314185","assets_url":"https://api.github.com/repos/stefansundin/altdrag/releases/314185/assets","upload_url":"https://uploads.github.com/repos/stefansundin/altdrag/releases/314185/assets{?name}","html_url":"https://github.com/stefansundin/altdrag/releases/tag/v0.2","id":314185,"tag_name":"v0.2","target_commitish":"master","name":"AltDrag v0.2","draft":false,"author":{"login":"stefansundin","id":1991151,"avatar_url":"https://avatars.githubusercontent.com/u/1991151?v=3","gravatar_id":"","url":"https://api.github.com/users/stefansundin","html_url":"https://github.com/stefansundin","followers_url":"https://api.github.com/users/stefansundin/followers","following_url":"https://api.github.com/users/stefansundin/following{/other_user}","gists_url":"https://api.github.com/users/stefansundin/gists{/gist_id}","starred_url":"https://api.github.com/users/stefansundin/starred{/owner}{/repo}","subscriptions_url":"https://api.github.com/users/stefansundin/subscriptions","organizations_url":"https://api.github.com/users/stefansundin/orgs","repos_url":"https://api.github.com/users/stefansundin/repos","events_url":"https://api.github.com/users/stefansundin/events{/privacy}","received_events_url":"https://api.github.com/users/stefansundin/received_events","type":"User","site_admin":false},"prerelease":false,"created_at":"2008-08-01T17:10:10Z","published_at":"2014-12-30T20:24:46Z","assets":[{"url":"https://api.github.com/repos/stefansundin/altdrag/releases/assets/132878","id":132878,"name":"AltDrag-0.2.7z","label":"","uploader":{"login":"stefansundin","id":1991151,"avatar_url":"https://avatars.githubusercontent.com/u/1991151?v=3","gravatar_id":"","url":"https://api.github.com/users/stefansundin","html_url":"https://github.com/stefansundin","followers_url":"https://api.github.com/users/stefansundin/followers","following_url":"https://api.github.com/users/stefansundin/following{/other_user}","gists_url":"https://api.github.com/users/stefansundin/gists{/gist_id}","starred_url":"https://api.github.com/users/stefansundin/starred{/owner}{/repo}","subscriptions_url":"https://api.github.com/users/stefansundin/subscriptions","organizations_url":"https://api.github.com/users/stefansundin/orgs","repos_url":"https://api.github.com/users/stefansundin/repos","events_url":"https://api.github.com/users/stefansundin/events{/privacy}","received_events_url":"https://api.github.com/users/stefansundin/received_events","type":"User","site_admin":false},"content_type":"application/octet-stream","state":"uploaded","size":9451,"download_count":3,"created_at":"2014-05-11T04:56:37Z","updated_at":"2014-05-11T04:56:39Z","browser_download_url":"https://github.com/stefansundin/altdrag/releases/download/v0.2/AltDrag-0.2.7z"}],"tarball_url":"https://api.github.com/repos/stefansundin/altdrag/tarball/v0.2","zipball_url":"https://api.github.com/repos/stefansundin/altdrag/zipball/v0.2","body":"2008-08-01:\r\n- You can no longer drag fullscreen windows.\r\n- The window is better placed when it's restored from its maximized state.\r\n"},{"url":"https://api.github.com/repos/stefansundin/altdrag/releases/314184","assets_url":"https://api.github.com/repos/stefansundin/altdrag/releases/314184/assets","upload_url":"https://uploads.github.com/repos/stefansundin/altdrag/releases/314184/assets{?name}","html_url":"https://github.com/stefansundin/altdrag/releases/tag/v0.1","id":314184,"tag_name":"v0.1","target_commitish":"master","name":"AltDrag v0.1","draft":false,"author":{"login":"stefansundin","id":1991151,"avatar_url":"https://avatars.githubusercontent.com/u/1991151?v=3","gravatar_id":"","url":"https://api.github.com/users/stefansundin","html_url":"https://github.com/stefansundin","followers_url":"https://api.github.com/users/stefansundin/followers","following_url":"https://api.github.com/users/stefansundin/following{/other_user}","gists_url":"https://api.github.com/users/stefansundin/gists{/gist_id}","starred_url":"https://api.github.com/users/stefansundin/starred{/owner}{/repo}","subscriptions_url":"https://api.github.com/users/stefansundin/subscriptions","organizations_url":"https://api.github.com/users/stefansundin/orgs","repos_url":"https://api.github.com/users/stefansundin/repos","events_url":"https://api.github.com/users/stefansundin/events{/privacy}","received_events_url":"https://api.github.com/users/stefansundin/received_events","type":"User","site_admin":false},"prerelease":false,"created_at":"2008-06-05T17:10:10Z","published_at":"2014-12-30T20:24:48Z","assets":[{"url":"https://api.github.com/repos/stefansundin/altdrag/releases/assets/132877","id":132877,"name":"AltDrag-0.1.7z","label":"","uploader":{"login":"stefansundin","id":1991151,"avatar_url":"https://avatars.githubusercontent.com/u/1991151?v=3","gravatar_id":"","url":"https://api.github.com/users/stefansundin","html_url":"https://github.com/stefansundin","followers_url":"https://api.github.com/users/stefansundin/followers","following_url":"https://api.github.com/users/stefansundin/following{/other_user}","gists_url":"https://api.github.com/users/stefansundin/gists{/gist_id}","starred_url":"https://api.github.com/users/stefansundin/starred{/owner}{/repo}","subscriptions_url":"https://api.github.com/users/stefansundin/subscriptions","organizations_url":"https://api.github.com/users/stefansundin/orgs","repos_url":"https://api.github.com/users/stefansundin/repos","events_url":"https://api.github.com/users/stefansundin/events{/privacy}","received_events_url":"https://api.github.com/users/stefansundin/received_events","type":"User","site_admin":false},"content_type":"application/octet-stream","state":"uploaded","size":9117,"download_count":3,"created_at":"2014-05-11T04:56:15Z","updated_at":"2014-05-11T04:56:18Z","browser_download_url":"https://github.com/stefansundin/altdrag/releases/download/v0.1/AltDrag-0.1.7z"}],"tarball_url":"https://api.github.com/repos/stefansundin/altdrag/tarball/v0.1","zipball_url":"https://api.github.com/repos/stefansundin/altdrag/zipball/v0.1","body":"2008-06-05:\r\n- Initial release."}]